CHANGELOG.md
LICENSE
README.md
django_datawatch/__init__.py
django_datawatch/admin.py
django_datawatch/apps.py
django_datawatch/base.py
django_datawatch/datawatch.py
django_datawatch/defaults.py
django_datawatch/forms.py
django_datawatch/models.py
django_datawatch/querysets.py
django_datawatch/tasks.py
django_datawatch/urls.py
django_datawatch/views.py
django_datawatch/backends/__init__.py
django_datawatch/backends/base.py
django_datawatch/backends/celery.py
django_datawatch/backends/synchronous.py
django_datawatch/common/__init__.py
django_datawatch/common/views.py
django_datawatch/locale/de/LC_MESSAGES/django.po
django_datawatch/management/__init__.py
django_datawatch/management/commands/__init__.py
django_datawatch/management/commands/datawatch_clean_up.py
django_datawatch/management/commands/datawatch_list_checks.py
django_datawatch/management/commands/datawatch_refresh_results.py
django_datawatch/management/commands/datawatch_run_checks.py
django_datawatch/migrations/0001_initial.py
django_datawatch/migrations/0002_auto_20180807_1508.py
django_datawatch/migrations/0003_resultstatushistory.py
django_datawatch/migrations/0004_resultassigneduser_resultassignedgroup_and_more.py
django_datawatch/migrations/0005_migrate_new_assigned_fields.py
django_datawatch/migrations/0006_remove_result_assigned_to_group_and_more.py
django_datawatch/migrations/0007_resulttag.py
django_datawatch/migrations/0008_alter_result_options.py
django_datawatch/migrations/__init__.py
django_datawatch/templates/django_datawatch/base.html
django_datawatch/templates/django_datawatch/dashboard.html
django_datawatch/templates/django_datawatch/detail.html
django_datawatch/templates/django_datawatch/form.html
django_datawatch/templates/django_datawatch/tags_manage.html
django_datawatch/templatetags/__init__.py
django_datawatch/templatetags/class_name.py
django_datawatch/tests/__init__.py
django_datawatch/tests/test_base_check.py
django_datawatch/tests/test_integration.py
django_datawatch-8.0.0.dist-info/METADATA
django_datawatch-8.0.0.dist-info/WHEEL
django_datawatch-8.0.0.dist-info/licenses/LICENSE
django_datawatch-8.0.0.dist-info/RECORD
