Metadata-Version: 2.4
Name: django-datawatch
Version: 8.0.0
Summary: Automated data checks for Django
Project-URL: Homepage, https://github.com/RegioHelden/django-datawatch
Project-URL: Documentation, https://github.com/RegioHelden/django-datawatch/blob/main/README.md
Project-URL: Repository, https://github.com/RegioHelden/django-datawatch.git
Project-URL: Issues, https://github.com/RegioHelden/django-datawatch/issues
Project-URL: Changelog, https://github.com/RegioHelden/django-datawatch/blob/main/CHANGELOG.md
Author-email: RegioHelden GmbH <opensource@regiohelden.de>
Maintainer-email: RegioHelden GmbH <opensource@regiohelden.de>
License-Expression: MIT
License-File: LICENSE
Keywords: check,checks,datawatch,django,monitoring
Classifier: Development Status :: 5 - Production/Stable
Classifier: Environment :: Web Environment
Classifier: Framework :: Django
Classifier: Intended Audience :: Developers
Classifier: License :: OSI Approved :: MIT License
Classifier: Operating System :: OS Independent
Classifier: Programming Language :: Python
Classifier: Programming Language :: Python :: 3
Classifier: Programming Language :: Python :: 3.10
Classifier: Programming Language :: Python :: 3.11
Classifier: Programming Language :: Python :: 3.12
Classifier: Programming Language :: Python :: 3.13
Classifier: Programming Language :: Python :: 3.14
Classifier: Topic :: Software Development
Classifier: Topic :: Software Development :: Libraries :: Python Modules
Requires-Python: >=3.10
Requires-Dist: celery>=5.0.0
Requires-Dist: django-extensions>=3.0.0
Requires-Dist: django-model-utils>=4.2.0
Requires-Dist: django<6.1,>=4.2
Requires-Dist: python-dateutil>=2.8.0
